google/auth/__init__.py
google/auth/_cloud_sdk.py
google/auth/_credentials_async.py
google/auth/_credentials_base.py
google/auth/_default.py
google/auth/_default_async.py
google/auth/_exponential_backoff.py
google/auth/_helpers.py
google/auth/_jwt_async.py
google/auth/_oauth2client.py
google/auth/_refresh_worker.py
google/auth/_service_account_info.py
google/auth/api_key.py
google/auth/app_engine.py
google/auth/aws.py
google/auth/credentials.py
google/auth/downscoped.py
google/auth/environment_vars.py
google/auth/exceptions.py
google/auth/external_account.py
google/auth/external_account_authorized_user.py
google/auth/iam.py
google/auth/identity_pool.py
google/auth/impersonated_credentials.py
google/auth/jwt.py
google/auth/metrics.py
google/auth/pluggable.py
google/auth/py.typed
google/auth/version.py
google/auth/aio/__init__.py
google/auth/aio/_helpers.py
google/auth/aio/credentials.py
google/auth/aio/transport/__init__.py
google/auth/aio/transport/aiohttp.py
google/auth/aio/transport/sessions.py
google/auth/compute_engine/__init__.py
google/auth/compute_engine/_metadata.py
google/auth/compute_engine/credentials.py
google/auth/crypt/__init__.py
google/auth/crypt/_cryptography_rsa.py
google/auth/crypt/_helpers.py
google/auth/crypt/_python_rsa.py
google/auth/crypt/base.py
google/auth/crypt/es256.py
google/auth/crypt/rsa.py
google/auth/transport/__init__.py
google/auth/transport/_aiohttp_requests.py
google/auth/transport/_custom_tls_signer.py
google/auth/transport/_http_client.py
google/auth/transport/_mtls_helper.py
google/auth/transport/_requests_base.py
google/auth/transport/grpc.py
google/auth/transport/mtls.py
google/auth/transport/requests.py
google/auth/transport/urllib3.py
google/oauth2/__init__.py
google/oauth2/_client.py
google/oauth2/_client_async.py
google/oauth2/_credentials_async.py
google/oauth2/_id_token_async.py
google/oauth2/_reauth_async.py
google/oauth2/_service_account_async.py
google/oauth2/challenges.py
google/oauth2/credentials.py
google_auth-2.40.1.dist-info/LICENSE
google_auth-2.40.1.dist-info/METADATA
google_auth-2.40.1.dist-info/WHEEL
google_auth-2.40.1.dist-info/top_level.txt
google_auth-2.40.1.dist-info/RECORD
