Metadata-Version: 2.1
Name: google-auth
Version: 2.40.1
Summary: Google Authentication Library
Home-page: https://github.com/googleapis/google-auth-library-python
Author: Google Cloud Platform
Author-email: googleapis-packages@google.com
License: Apache 2.0
Keywords: google auth oauth client
Classifier: Programming Language :: Python :: 3
Classifier: Programming Language :: Python :: 3.7
Classifier: Programming Language :: Python :: 3.8
Classifier: Programming Language :: Python :: 3.9
Classifier: Programming Language :: Python :: 3.10
Classifier: Programming Language :: Python :: 3.11
Classifier: Programming Language :: Python :: 3.12
Classifier: Programming Language :: Python :: 3.13
Classifier: Development Status :: 5 - Production/Stable
Classifier: Intended Audience :: Developers
Classifier: License :: OSI Approved :: Apache Software License
Classifier: Operating System :: POSIX
Classifier: Operating System :: Microsoft :: Windows
Classifier: Operating System :: MacOS :: MacOS X
Classifier: Operating System :: OS Independent
Classifier: Topic :: Internet :: WWW/HTTP
Requires-Python: >=3.7
License-File: LICENSE
Requires-Dist: cachetools<6.0,>=2.0.0
Requires-Dist: pyasn1-modules>=0.2.1
Requires-Dist: rsa<5,>=3.1.4
Provides-Extra: aiohttp
Requires-Dist: aiohttp<4.0.0,>=3.6.2; extra == "aiohttp"
Requires-Dist: requests<3.0.0,>=2.20.0; extra == "aiohttp"
Provides-Extra: enterprise-cert
Requires-Dist: cryptography; extra == "enterprise-cert"
Requires-Dist: pyopenssl; extra == "enterprise-cert"
Provides-Extra: pyopenssl
Requires-Dist: pyopenssl>=20.0.0; extra == "pyopenssl"
Requires-Dist: cryptography>=38.0.3; extra == "pyopenssl"
Requires-Dist: cryptography<39.0.0; python_version < "3.8" and extra == "pyopenssl"
Provides-Extra: pyjwt
Requires-Dist: pyjwt>=2.0; extra == "pyjwt"
Requires-Dist: cryptography>=38.0.3; extra == "pyjwt"
Requires-Dist: cryptography<39.0.0; python_version < "3.8" and extra == "pyjwt"
Provides-Extra: reauth
Requires-Dist: pyu2f>=0.1.5; extra == "reauth"
Provides-Extra: requests
Requires-Dist: requests<3.0.0,>=2.20.0; extra == "requests"
Provides-Extra: testing
Requires-Dist: grpcio; extra == "testing"
Requires-Dist: flask; extra == "testing"
Requires-Dist: freezegun; extra == "testing"
Requires-Dist: mock; extra == "testing"
Requires-Dist: oauth2client; extra == "testing"
Requires-Dist: pyjwt>=2.0; extra == "testing"
Requires-Dist: cryptography>=38.0.3; extra == "testing"
Requires-Dist: cryptography<39.0.0; python_version < "3.8" and extra == "testing"
Requires-Dist: pytest; extra == "testing"
Requires-Dist: pytest-cov; extra == "testing"
Requires-Dist: pytest-localserver; extra == "testing"
Requires-Dist: pyopenssl>=20.0.0; extra == "testing"
Requires-Dist: cryptography>=38.0.3; extra == "testing"
Requires-Dist: cryptography<39.0.0; python_version < "3.8" and extra == "testing"
Requires-Dist: pyu2f>=0.1.5; extra == "testing"
Requires-Dist: responses; extra == "testing"
Requires-Dist: urllib3; extra == "testing"
Requires-Dist: packaging; extra == "testing"
Requires-Dist: aiohttp<4.0.0,>=3.6.2; extra == "testing"
Requires-Dist: requests<3.0.0,>=2.20.0; extra == "testing"
Requires-Dist: aioresponses; extra == "testing"
Requires-Dist: pytest-asyncio; extra == "testing"
Requires-Dist: pyopenssl<24.3.0; extra == "testing"
Requires-Dist: aiohttp<3.10.0; extra == "testing"
Provides-Extra: urllib3
Requires-Dist: urllib3; extra == "urllib3"
Requires-Dist: packaging; extra == "urllib3"
